blackjack.py
Score/__init__.py
utils/__init__.py
utils/utils.py
BlackjackByIkers-1.1.0.dist-info/LICENSE
BlackjackByIkers-1.1.0.dist-info/METADATA
BlackjackByIkers-1.1.0.dist-info/WHEEL
BlackjackByIkers-1.1.0.dist-info/top_level.txt
BlackjackByIkers-1.1.0.dist-info/RECORD
